stellars-0.1.1.dist-info/METADATA
stellars-0.1.1.dist-info/WHEEL
stellars-0.1.1.dist-info/licenses/LICENSE
stellars/__init__.py
stellars/stellars.abi3.so
stellars-0.1.1.dist-info/RECORD
