Metadata-Version: 2.4
Name: stellars
Version: 0.1.1
Classifier: Development Status :: 3 - Alpha
Classifier: Intended Audience :: Science/Research
Classifier: License :: OSI Approved :: MIT License
Classifier: Programming Language :: Rust
Classifier: Programming Language :: Python :: Implementation :: CPython
Classifier: Programming Language :: Python :: Implementation :: PyPy
Classifier: Programming Language :: Python :: 3.10
Classifier: Programming Language :: Rust
License-File: LICENSE
Summary: High-performance phylogenetic analysis extensions for Cassiopeia
Keywords: phylogenetics,lineage-tracing,cassiopeia,bioinformatics
Author-email: Pedro Olivares Chauvet <pedro.olivares@weizmann.ac.il>
License: MIT
Requires-Python: >=3.8
